BİLGİSAYAR ORGANİZASYONU/UYGULAMALAR/uygulama2/HW2/RiscV_SingleCycle.v
module RiscV_SingleCycle(
    input clk,
    input reset,
    output reg [31:0] pc,
    input [31:0] instruction,
    output reg [31:0] alu_result,
    output [31:0] write_data,
    input [31:0] read_data
);

    // PC register and Next PC logic
    reg [31:0] next_pc;

    always @(posedge clk or posedge reset) begin
        if (reset) 
            pc <= 32'b0;
        else 
            pc <= next_pc;
    end

    // Instruction Decode
    wire [6:0] opcode;
    wire [4:0] rd, rs1, rs2;
    wire [2:0] funct3;
    wire [6:0] funct7;
    wire [31:0] sign_extended_imm;

    assign opcode = instruction[6:0];
    assign rd = instruction[11:7];
    assign rs1 = instruction[19:15];
    assign rs2 = instruction[24:20];
    assign funct3 = instruction[14:12];
    assign funct7 = instruction[31:25];
    assign sign_extended_imm = 32'sd123; 

    // Register File
    reg [31:0] registers[31:0];
    always @(posedge clk) begin
        if (!reset && instruction[5:0] != 6'b000000 && opcode != 7'b1101111)
            registers[rd] <= alu_result;  // Write back to the register file, exclude jal
    end
    assign write_data = registers[rd];

    wire [31:0] rs1_data = registers[rs1];
    wire [31:0] rs2_data = registers[rs2];

    // ALU
    reg [31:0] alu_out;

    always @(*) begin
        case (opcode)
            7'b0110011: begin  // R-type
                case (funct3)
                    3'b000: begin
                        if (funct7 == 7'b0000000)
                            alu_out = rs1_data + rs2_data;  // ADD
                        else if (funct7 == 7'b0100000)
                            alu_out = rs1_data - rs2_data;  // SUB
                    end
                    3'b101: begin
                        if (funct7 == 7'b0000000)
                            alu_out = rs1_data >> rs2_data[4:0];  // Logical shift right (SRL)
                        else if (funct7 == 7'b0100000)
                            alu_out = $signed(rs1_data) >>> rs2_data[4:0];  // Arithmetic shift right (SRA)
                    end
                    3'b110: alu_out = rs1_data | rs2_data;  // OR
                    3'b111: alu_out = rs1_data & rs2_data;  // AND
                    3'b010: alu_out = ($signed(rs1_data) < $signed(rs2_data)) ? 1 : 0;  // SLT
                endcase
            end
            7'b0000011: alu_out = rs1_data + sign_extended_imm; // LW
            7'b0100011: alu_out = rs1_data + sign_extended_imm; // SW
            7'b0010011: begin  // I-type ALU operations
                case (funct3)
                    3'b000: alu_out = rs1_data + sign_extended_imm;  // ADDI
                    3'b110: alu_out = rs1_data | sign_extended_imm;  // ORI
                    3'b111: alu_out = rs1_data & sign_extended_imm;  // ANDI
                    3'b010: alu_out = ($signed(rs1_data) < $signed(sign_extended_imm)) ? 1 : 0;  // SLTI
                endcase
            end
        endcase
    end

    // Data Memory Interaction
    always @(posedge clk) begin
        if (opcode == 7'b0000011)  // LW
            alu_result <= read_data;

        else
            alu_result <= alu_out;
    end

    // Initialize next_pc
    always @(posedge clk or posedge reset) begin
        if (reset)
            next_pc <= 32'b0;
        else if (opcode != 7'b1100011 && opcode != 7'b1101111)
            next_pc <= pc + 4;  // Default increment
        else if (opcode == 7'b1101111)
            next_pc <= pc + sign_extended_imm; //JAL
    end

endmodule

BİLGİSAYAR ORGANİZASYONU/UYGULAMALAR/uygulama2/HW2/TestBench.v
module TestBench;

    reg clk = 0;
    reg reset = 0;
    wire [31:0] pc;
    wire [31:0] alu_result;
    wire [31:0] write_data;
    reg [31:0] instruction;
    reg [31:0] read_data;

    RiscV_SingleCycle dut (
        .clk(clk),
        .reset(reset),
        .pc(pc),
        .instruction(instruction),
        .alu_result(alu_result),
        .write_data(write_data),
        .read_data(read_data)
    );

    always #5 clk = !clk;  // Clock generation

    initial begin
        $dumpfile("processor_sim.vcd");
        $dumpvars(0, TestBench);

        reset = 1;
        #10;
        reset = 0;

        // Initialize register values (example: R10 = 5, R11 = 4, R12 = 3)
        dut.registers[10] = 5;  // R10
        dut.registers[11] = 4;  // R11
        dut.registers[12] = 3;  // R12
        read_data = 123;  // Simulate read data for LW

        // ADD R8, R10, R11
        instruction = 32'b0000000_01011_01010_000_01000_0110011;
        #10;
        // OR R8, R10, R11
        instruction = 32'b0000000_01011_01010_110_01000_0110011;
        #10;
        // AND R8, R10, R11
        instruction = 32'b0000000_01011_01010_111_01000_0110011;
        #10;
        // SLT R8, R10, R11
        instruction = 32'b0000000_01011_01010_010_01000_0110011;
        #10;
        // ADDI R8, R10, #9 (Immediate Add)
        instruction = 32'b00000000000001010_000_01000_0010011;  // imm[11:0] rs1 funct3 rd opcode
        #10;
        // SLTI R8, R10, #7 (Set less than immediate)
        instruction = 32'b00000000000001010_010_01000_0010011;
        #10;
        // ANDI R8, R10, #15 (AND immediate)
        instruction = 32'b00000000000001010_111_01000_0010011;
        #10;
        // ORI R8, R10, #12 (OR immediate)
        instruction = 32'b00000000000001010_110_01000_0010011;
        #10;
        // LW R8, 4(R10) (Load word)
        instruction = 32'b00000000010001010_010_01000_0000011;  // imm[11:0] rs1 funct3 rd opcode
        #10;
        // SW R8, 4(R10) (Store word)
        instruction = 32'b00000000010001000_010_01010_0100011;  // imm[11:5] rs2 rs1 funct3 imm[4:0] opcode
        #10;
        // Testing JAL: should jump to address PC + 16 and set R8 to the next instruction address (PC + 4)
        instruction = 32'b00000000000100000_00000_000_01000_1101111;  // imm[20] imm[10:1] imm[11] imm[19:12] rd opcode
        #20;  // Need more time for jump to be visible
        // Testing BEQ: Should branch if R10 equals R11
        instruction = 32'b0000000_01011_01010_000_00000_1100011;  // imm[12:1] rs2 rs1 funct3 imm[11] imm[12] opcode
        #10;
        // Instruction after BEQ, should not execute if branch taken
        instruction = 32'b0000000_01100_01010_000_01000_0110011;  // ADD R8, R10, R12 (Should not execute if BEQ takes)
        #10;

        // Testing SRA: Shift Right Arithmetic
        dut.registers[10] = 32'hFFFFF830;  // Negative number to demonstrate sign extension
        dut.registers[11] = 4;             // Shift by 4 bits
        instruction = 32'b0100000_01011_01010_101_01000_0110011;  // SRA R8, R10, R11
        #10;

        $finish;  // Ends the simulation
    end

endmodule

BİLGİSAYAR ORGANİZASYONU/UYGULAMALAR/uygulama2/HW2/processor_sim.vcd
$date
	Fri May 03 13:03:45 2024
$end
$version
	Icarus Verilog
$end
$timescale
	1s
$end
$scope module TestBench $end
$var wire 32 ! write_data [31:0] $end
$var wire 32 " pc [31:0] $end
$var wire 32 # alu_result [31:0] $end
$var reg 1 $ clk $end
$var reg 32 % instruction [31:0] $end
$var reg 32 & read_data [31:0] $end
$var reg 1 ' reset $end
$scope module dut $end
$var wire 1 $ clk $end
$var wire 32 ( instruction [31:0] $end
$var wire 32 ) read_data [31:0] $end
$var wire 1 ' reset $end
$var wire 32 * rs1_data [31:0] $end
$var wire 32 + rs2_data [31:0] $end
$var wire 32 , sign_extended_imm [31:0] $end
$var wire 32 - write_data [31:0] $end
$var wire 5 . rs2 [4:0] $end
$var wire 5 / rs1 [4:0] $end
$var wire 5 0 rd [4:0] $end
$var wire 7 1 opcode [6:0] $end
$var wire 7 2 funct7 [6:0] $end
$var wire 3 3 funct3 [2:0] $end
$var reg 32 4 alu_out [31:0] $end
$var reg 32 5 alu_result [31:0] $end
$var reg 32 6 next_pc [31:0] $end
$var reg 32 7 pc [31:0] $end
$upscope $end
$upscope $end
$enddefinitions $end
$comment Show the parameter values. $end
$dumpall
$end
#0
$dumpvars
b0 7
b0 6
bx 5
bx 4
bx 3
bx 2
bx 1
bx 0
bx /
bx .
bx -
b1111011 ,
bx +
bx *
bx )
bx (
1'
bx &
bx %
0$
bx #
b0 "
bx !
$end
#5
1$
#10
b1001 4
b110011 1
b1000 0
b101 *
b1010 /
b100 +
b1011 .
b0 3
b0 2
0$
b101101010000010000110011 %
b101101010000010000110011 (
b1111011 &
b1111011 )
0'
#15
b100 6
b1001 #
b1001 5
1$
#20
b101 4
b110 3
0$
b101101010110010000110011 %
b101101010110010000110011 (
#25
b100 "
b100 7
b1001 !
b1001 -
b101 #
b101 5
1$
#30
b100 4
b111 3
0$
b101101010111010000110011 %
b101101010111010000110011 (
#35
b1000 6
b100 #
b100 5
b101 !
b101 -
1$
#40
b0 4
b10 3
0$
b101101010010010000110011 %
b101101010010010000110011 (
#45
b1000 "
b1000 7
b100 !
b100 -
b0 #
b0 5
1$
#50
b10000000 4
b10011 1
bx +
b0 .
b0 3
0$
b1010000010000010011 %
b1010000010000010011 (
#55
b1100 6
b10000000 #
b10000000 5
b0 !
b0 -
1$
#60
b1 4
b10 3
0$
b1010010010000010011 %
b1010010010000010011 (
#65
b1100 "
b1100 7
b10000000 !
b10000000 -
b1 #
b1 5
1$
#70
b111 3
0$
b1010111010000010011 %
b1010111010000010011 (
#75
b10000 6
b1 !
b1 -
1$
#80
b1111111 4
b110 3
0$
b1010110010000010011 %
b1010110010000010011 (
#85
b10000 "
b10000 7
b1111111 #
b1111111 5
1$
#90
b10000000 4
b11 1
b100 .
b10 3
0$
b10001010010010000000011 %
b10001010010010000000011 (
#95
b10100 6
b1111011 #
b1111011 5
b1111111 !
b1111111 -
1$
#100
b11111010 4
b100011 1
b101 !
b101 -
b1010 0
b1111111 *
b1000 /
0$
b10001000010010100100011 %
b10001000010010100100011 (
#105
b10100 "
b10100 7
b1111011 !
b1111011 -
1$
#110
b1101111 1
b1111111 !
b1111111 -
b1000 0
bx *
b0 /
b0 .
b0 3
b1 2
0$
b10000000000000010001101111 %
b10000000000000010001101111 (
#115
b10001111 6
b11111010 #
b11111010 5
1$
#120
0$
#125
b10001111 "
b10001111 7
1$
#130
b1100011 1
bx !
bx -
b0 0
b1111011 *
b1010 /
b100 +
b1011 .
b0 2
0$
b101101010000000001100011 %
b101101010000000001100011 (
#135
b11111010 !
b11111010 -
1$
#140
b1111110 4
b110011 1
b1111111 !
b1111111 -
b1000 0
b11 +
b1100 .
0$
b110001010000010000110011 %
b110001010000010000110011 (
#145
b10010011 6
b11111010 !
b11111010 -
b1111110 #
b1111110 5
1$
#150
b100 +
b1011 .
b101 3
b100000 2
b11111111111111111111111110000011 4
0$
b1000000101101010101010000110011 %
b1000000101101010101010000110011 (
b11111111111111111111100000110000 *
#155
b10010011 "
b10010011 7
b11111111111111111111111110000011 #
b11111111111111111111111110000011 5
b1111110 !
b1111110 -
1$
